
  [ {
        "pitanje": "What is the Capital of Finland?",
        "tacanOdg": "Helsinki",
        "pogresanOdg1": "Oslo",
        "pogresanOdg2": "Kopenhagen",
        "pogresanOdg3": "Stockholm"
    },
    {
        "pitanje": "In what year did World War II end?",
        "tacanOdg": 1945,
        "pogresanOdg1": 1944,
        "pogresanOdg2": 1918,
        "pogresanOdg3": 1919
    },
    {
        "pitanje": "Which planet is the warmest in the solar system?",
        "tacanOdg": "Venus",
        "pogresanOdg1": "Mars",
        "pogresanOdg2": "Earth",
        "pogresanOdg3": "Mercury"
    },
    {
        "pitanje": "In what country was Caesar salad made?",
        "tacanOdg": "Mexico",
        "pogresanOdg1": "Italy",
        "pogresanOdg2": "Spain",
        "pogresanOdg3": "Brazil"
    },
    {
        "pitanje": "How many hearts does an octopus have?",
        "tacanOdg": 3,
        "pogresanOdg1": 2,
        "pogresanOdg2": 5,
        "pogresanOdg3": 1
    },
    {
        "pitanje": "How long is an Olympic swimming pool (in meters)?",
        "tacanOdg": "50 meters",
        "pogresanOdg1": "100 meters",
        "pogresanOdg2": "25 meters",
        "pogresanOdg3": "75 meters"
    },
    {
        "pitanje": "Which of the kings in the playing cards doesn't have a mustache?",
        "tacanOdg": "King of Hertz",
        "pogresanOdg1": "King of Spade",
        "pogresanOdg2": "King of Diamonds",
        "pogresanOdg3": "Every king has a mustache"
    },
    {
        "pitanje": "If we know that an environment is basic, its pH value will be:",
        "tacanOdg": "pH>7",
        "pogresanOdg1": "pH=7",
        "pogresanOdg2": "pH<7",
        "pogresanOdg3": "pH<0.7"
    },
    {
        "pitanje": "The mythological creature that had a goat's body, a snake's tail and a lion's head is called:",
        "tacanOdg": "Chimera",
        "pogresanOdg1": "Satyr",
        "pogresanOdg2": "Kerberos",
        "pogresanOdg3": "Medusa"
    },
    {
        "pitanje": "If in a vacuum, from a height of 3 meters, we throw a metal coin, a pen, a mobile phone and a pen at the same time, what will fall to the ground the fastest?",
        "tacanOdg": "None of the above",
        "pogresanOdg1": "Pencil",
        "pogresanOdg2": "Phone",
        "pogresanOdg3": "Feather"
    }
    

]